{
  "url": "https://www.kickstarter.com/projects/1846044799/learning-kit-explore-electronics-in-biomedical-application",
  "campaign_details": {
    "funding_period_text": "Funding period\nFeb 21 2025 - Mar 18 2025 (25 days)",
    "funding_start_date": "2025-02-20T18:16:09-05:00",
    "funding_end_date": "2025-03-17T18:16:09-04:00",
    "funding_duration_days": 25,
    "pledged_amount": "CA$ 20,614",
    "funding_goal": "CA$ 2,500",
    "backers_count": "63"
  },
  "updates": {
    "count": 0,
    "content": []
  }
}