{
  "url": "https://www.kickstarter.com/projects/sazalem/preserving-culture-of-central-asia",
  "campaign_details": {
    "funding_period_text": "Funding period\nJan 27 2025 - Mar 27 2025 (59 days)",
    "funding_start_date": "2025-01-27T00:00:00.000000Z",
    "funding_end_date": "2025-03-27T23:01:16.364086Z",
    "funding_duration_days": 59,
    "pledged_amount": "S$ 21",
    "funding_goal": "S$ 123,021",
    "backers_count": "3",
    "days_left": 3,
    "project_launch_text": "Project launches JANUARY 27, 2025"
  },
  "updates": {
    "count": 0,
    "content": []
  }
}