{
  "url": "https://www.kickstarter.com/projects/shortflixx/short-flixx-a-short-video-social-media-app-born-in-the-usa",
  "campaign_details": {
    "funding_period_text": "Funding period\nMar 17 2025 - Apr 15 2025 (29 days)",
    "funding_start_date": "2025-03-17T00:00:00.000000Z",
    "funding_end_date": "2025-04-15T19:45:43.399258Z",
    "funding_duration_days": 29,
    "pledged_amount": "S$ 0",
    "funding_goal": "S$ 52,439",
    "backers_count": "0",
    "days_left": 20,
    "project_launch_text": "Project launches MARCH 17, 2025"
  },
  "updates": {
    "count": 0,
    "content": []
  }
}