{
  "url": "https://www.kickstarter.com/projects/1383816306/timesheetio-work-log-get-your-money",
  "campaign_details": {
    "funding_period_text": "Funding period\nJan 27 2025 - Mar 28 2025 (60 days)",
    "funding_start_date": "2025-01-27T00:00:00.000000Z",
    "funding_end_date": "2025-03-28T19:39:16.776593Z",
    "funding_duration_days": 60,
    "pledged_amount": "S$ 434",
    "funding_goal": "S$ 21,703",
    "backers_count": "2",
    "days_left": 4,
    "project_launch_text": "Project launches JANUARY 27, 2025"
  },
  "updates": {
    "count": 0,
    "content": []
  }
}