{
  "url": "https://www.kickstarter.com/projects/30812010/threesixfive-1980s-themed-supernatural-movie",
  "campaign_details": {
    "funding_period_text": "Funding period\nJun 16 2018 - Jul 16 2018 (30 days)",
    "funding_start_date": "2018-06-16T10:41:25-04:00",
    "funding_end_date": "2018-07-16T10:41:25-04:00",
    "funding_duration_days": 30,
    "pledged_amount": "S$ 27",
    "funding_goal": "S$ 25,880",
    "backers_count": "2"
  },
  "updates": {
    "count": 0,
    "content": []
  }
}